ebc/__init__.py
ebc/_version.py
ebc/py.typed
ebc/config_proxy/__init__.py
ebc/log_helper/__init__.py
ebc/worker_manager/__init__.py
ebc/worker_manager/__main__.py
elice_backend_components-25.2.1.dist-info/METADATA
elice_backend_components-25.2.1.dist-info/WHEEL
elice_backend_components-25.2.1.dist-info/top_level.txt
elice_backend_components-25.2.1.dist-info/RECORD
