Metadata-Version: 2.1
Name: elice-backend-components
Version: 25.2.1
Summary: Components for building elice-backend projects
Author: elice.io
Author-email: contact@elice.io
Classifier: Development Status :: 5 - Production/Stable
Classifier: Programming Language :: Python :: 3.8
Classifier: Programming Language :: Python :: 3.9
Classifier: Programming Language :: Python :: 3.10
Classifier: Programming Language :: Python :: 3.11
Classifier: Programming Language :: Python :: 3.12
Classifier: Programming Language :: Python :: Implementation :: CPython
Classifier: Operating System :: POSIX
Classifier: Operating System :: MacOS :: MacOS X
Requires-Python: <3.13,>=3.8
Requires-Dist: sentry-sdk <3,>=2.14.0
Provides-Extra: dev
Requires-Dist: bandit ; extra == 'dev'
Requires-Dist: flake8-bugbear ; extra == 'dev'
Requires-Dist: flake8-datetimez ; extra == 'dev'
Requires-Dist: flake8-isort ; extra == 'dev'
Requires-Dist: flake8 ; extra == 'dev'
Requires-Dist: mypy ; extra == 'dev'
Requires-Dist: pip-tools ; extra == 'dev'
Requires-Dist: black ; extra == 'dev'
